cyberfusion/SystemdSupport/__init__.py
cyberfusion/SystemdSupport/_constants.py
cyberfusion/SystemdSupport/manager.py
cyberfusion/SystemdSupport/tmp_files.py
cyberfusion/SystemdSupport/units.py
python3_cyberfusion_systemd_support-2.3.1.dist-info/METADATA
python3_cyberfusion_systemd_support-2.3.1.dist-info/WHEEL
python3_cyberfusion_systemd_support-2.3.1.dist-info/top_level.txt
python3_cyberfusion_systemd_support-2.3.1.dist-info/RECORD
