Metadata-Version: 2.4
Name: python3-cyberfusion-systemd-support
Version: 2.3.1
Summary: Library for systemd.
Author-email: Cyberfusion <support@cyberfusion.io>
Project-URL: Source, https://github.com/CyberfusionIO/python3-cyberfusion-systemd-support
Requires-Dist: python3-cyberfusion-common~=2.12
